{"id":"8QSIrVCbAcmZF3b90r6p4","title":"Functional","vault":{"fsPath":"vault"},"type":"note","desc":"","links":[{"from":{"fname":"root","vaultName":"vault"},"type":"backlink","position":{"start":{"line":84,"column":3,"offset":1174},"end":{"line":84,"column":40,"offset":1211},"indent":[]},"value":"domain.functional"}],"anchors":{"seemingly-impossible-functional-programs":{"type":"header","text":"Seemingly impossible functional programs","value":"seemingly-impossible-functional-programs","line":8,"column":0}},"fname":"domain.functional","updated":1637263411123,"created":1637263394535,"parent":"nQ25lsPGG0GZgyiC9mRNT","children":[],"data":{},"contentHash":"3f0945ce421d3ac6f84c90d04573cfd5","custom":{}}
