{"id":"dy9k1oRVoe6i3l6bzvKos","title":"System Design","vault":{"fsPath":"vault"},"type":"note","desc":"","links":[{"from":{"fname":"root","vaultName":"vault"},"type":"backlink","position":{"start":{"line":69,"column":3,"offset":833},"end":{"line":69,"column":44,"offset":874},"indent":[]},"value":"tech.system-design"}],"anchors":{"how-mdns-autocomplete-search-works":{"type":"header","text":"How MDN’s autocomplete search works","value":"how-mdns-autocomplete-search-works","line":8,"column":0},"png":{"type":"header","text":"PNG","value":"png","line":12,"column":0},"scaling-monorepo-maintenance":{"type":"header","text":"Scaling Monorepo Maintenance","value":"scaling-monorepo-maintenance","line":16,"column":0},"query-engines-push-vs-pull":{"type":"header","text":"Query Engines: Push vs. Pull","value":"query-engines-push-vs-pull","line":20,"column":0},"diving-deep-on-s3-consistency":{"type":"header","text":"Diving Deep on S3 Consistency","value":"diving-deep-on-s3-consistency","line":24,"column":0},"deep-dive-in-cors":{"type":"header","text":"Deep Dive in CORS","value":"deep-dive-in-cors","line":28,"column":0},"demystifying-programs-that-create-programs-part-1-a-disassembler":{"type":"header","text":"Demystifying programs that create programs, part 1: A disassembler","value":"demystifying-programs-that-create-programs-part-1-a-disassembler","line":32,"column":0},"how-to-implement-a-hash-table-in-c":{"type":"header","text":"How to implement a hash table (in C)","value":"how-to-implement-a-hash-table-in-c","line":36,"column":0},"a-visual-guide-to-ssh-tunnels":{"type":"header","text":"A visual guide to SSH tunnels","value":"a-visual-guide-to-ssh-tunnels","line":40,"column":0},"os-projects":{"type":"header","text":"OS Projects","value":"os-projects","line":44,"column":0},"nand2tetris":{"type":"header","text":"Nand2Tetris","value":"nand2tetris","line":48,"column":0},"load-balancing-and-its-different-types":{"type":"header","text":"Load balancing and its different types","value":"load-balancing-and-its-different-types","line":52,"column":0},"build-your-own-async-primitive":{"type":"header","text":"Build Your own Async Primitive","value":"build-your-own-async-primitive","line":56,"column":0}},"fname":"tech.system-design","updated":1637275838084,"created":1637269418874,"parent":"RJpOess77XPb82EqcdaaZ","children":[],"data":{},"contentHash":"f635b7bb8b2212b00a070466556a3175","custom":{}}
