{"id":"QLiU2dw0UTwMgfciEHd7F","title":"Personal Finance","vault":{"fsPath":"vault"},"type":"note","desc":"","links":[{"from":{"fname":"root","vaultName":"vault"},"type":"backlink","position":{"start":{"line":89,"column":3,"offset":1389},"end":{"line":89,"column":52,"offset":1438},"indent":[]},"value":"domain.personal-finance"}],"anchors":{"projectifi---model-and-simulate-your-financial-future":{"type":"header","text":"ProjectiFi - Model and Simulate your Financial Future","value":"projectifi---model-and-simulate-your-financial-future","line":8,"column":0},"spreadsheet-formulas-for-personal-finance":{"type":"header","text":"Spreadsheet Formulas for Personal Finance","value":"spreadsheet-formulas-for-personal-finance","line":12,"column":0},"first-time-buyer-lorenz-curves":{"type":"header","text":"First-time Buyer Lorenz Curves","value":"first-time-buyer-lorenz-curves","line":16,"column":0},"the-ultimate-guide-to-inflation":{"type":"header","text":"The Ultimate Guide to Inflation","value":"the-ultimate-guide-to-inflation","line":20,"column":0}},"fname":"domain.personal-finance","updated":1637271805207,"created":1637265097856,"parent":"nQ25lsPGG0GZgyiC9mRNT","children":[],"data":{},"contentHash":"6a6cdecd7eb7ae3910d3b3250e12ac48","custom":{}}
